Workbook

Sheet Data
A1: Full Name | B1: Job Title | C1: Company Name | D1: Experience | E1: Skills 1 | F1: Skills 2 | G1: linkedinPublicUrl | H1: city | I1: state | J1: country | L1: Email
A2: SanjaiReddi BE,ME(D) | B2: CHIEF EXECUTIVE | D2: 14+ | E2: Account Management | F2: Data Analysis | G2: https://www.linkedin.com/in/sanjaireddi-be-me-d-098bb84b | H2: Coimbatore | I2: India | J2: India | L2: =IFERROR(_xlfn.XLOOKUP(TRIM(G2), Sheet1!$C:$C, Sheet1!$E:$E), "")
A3: Henry Wald | B3: Engineer | C3: Specsys Inc. | D3: 4+ | E3: Troubleshooting | F3: Mechanical Engineering | G3: https://www.linkedin.com/in/henry-wald-07b4551a1 | H3: Minneapolis | I3: United Kingdom | J3: United States | L3: =IFERROR(_xlfn.XLOOKUP(TRIM(G3), Sheet1!$C:$C, Sheet1!$E:$E), "")
A4: Saket Sankhla | B4: Business Process Transformation Leader | C4: Schneider Electric | D4: 1+ | E4: Manufacturing Process Improvement | F4: Legacy Modernization | G4: https://www.linkedin.com/in/saket-sankhla | H4: Boston | I4: Oman | J4: United States | L4: =IFERROR(_xlfn.XLOOKUP(TRIM(G4), Sheet1!$C:$C, Sheet1!$E:$E), "")
A5: BRAGADEESH V | B5: Ex-Application Development Intern | C5: Citi India | D5: 0.7 | E5: Problem Solving | F5: Databases | G5: https://www.linkedin.com/in/bragadeesh05 | H5: Tiruppur | I5: India | J5: India | L5: =IFERROR(_xlfn.XLOOKUP(TRIM(G5), Sheet1!$C:$C, Sheet1!$E:$E), "")
A6: Akshama Panwar | B6: Team Lead | D6: 4+ | G6: https://www.linkedin.com/in/akshama-panwar-580b2a70 | H6: Randolph | I6: Canada | J6: United States | L6: =IFERROR(_xlfn.XLOOKUP(TRIM(G6), Sheet1!$C:$C, Sheet1!$E:$E), "")
A7: Shakthi S. Shanmugam | B7: Paid Media Manager | C7: Klatch | D7: 0.2 | E7: Interpersonal Skills | F7: Attention to Detail | G7: https://www.linkedin.com/in/sakthivelshanmugam | H7: Brighton | I7: Qatar | J7: United Kingdom | L7: =IFERROR(_xlfn.XLOOKUP(TRIM(G7), Sheet1!$C:$C, Sheet1!$E:$E), "")
A8: Arun Raj k | B8: HR Executive | C8: Crux Prestressing Systems | D8: 2 | E8: Recruiting | F8: Information Technology | G8: https://www.linkedin.com/in/arun-raj-k-890274193 | H8: Hyderabad | I8: Saudi Arabia | J8: India | L8: =IFERROR(_xlfn.XLOOKUP(TRIM(G8), Sheet1!$C:$C, Sheet1!$E:$E), "")
A9: Anjali Balakrishnan | B9: Regional Strategy Manager | C9: Signify Health | D9: 1 | E9: Due Diligence | F9: Financial Modeling | G9: https://www.linkedin.com/in/anjali-balakrishnan-3b971217a | H9: Chicago | I9: Indonesia | J9: United States | L9: =IFERROR(_xlfn.XLOOKUP(TRIM(G9), Sheet1!$C:$C, Sheet1!$E:$E), "")
A10: Rogel D. | B10: Data Migration Specialist | C10: Global Relay | D10: 3+ | E10: Administrative Assistance | F10: Problem Solving | G10: https://www.linkedin.com/in/rogel-d-4b182548 | H10: Vancouver | I10: Germany | J10: Canada | L10: =IFERROR(_xlfn.XLOOKUP(TRIM(G10), Sheet1!$C:$C, Sheet1!$E:$E), "")
A11: Vignesh GS | B11: Consulting Partner | C11: Era Group - North America | D11: 2+ | E11: Sales | F11: Product Operations | G11: https://www.linkedin.com/in/gsvignesh | H11: Atlanta | I11: United States | J11: United States | L11: =IFERROR(_xlfn.XLOOKUP(TRIM(G11), Sheet1!$C:$C, Sheet1!$E:$E), "")
A12: Angeline Benjamin | B12: Action Coach with Results | D12: 9+ | E12: Food Safety | F12: Food | G12: https://www.linkedin.com/in/angelinebenjamin | H12: Queen Creek | I12: California | J12: United States | L12: =IFERROR(_xlfn.XLOOKUP(TRIM(G12), Sheet1!$C:$C, Sheet1!$E:$E), "")
A13: Varnell Smith | B13: Senior Talent Acquisition Professional | D13: 11+ | E13: Human Resources | F13: Temporary Placement | G13: https://www.linkedin.com/in/varnell-smith-9702935 | H13: N/A | I13: N/A | J13: N/A | L13: =IFERROR(_xlfn.XLOOKUP(TRIM(G13), Sheet1!$C:$C, Sheet1!$E:$E), "")
A14: Chandra Shekar Sarap | B14: Vice President Research & Development - Data Science | C14: Valtep | D14: 0.8 | E14: multiscale modelling | F14: Graphene | G14: https://www.linkedin.com/in/chandra-shekar-sarap-85a89145 | H14: Hyderabad | I14: Saudi Arabia | J14: India | L14: =IFERROR(_xlfn.XLOOKUP(TRIM(G14), Sheet1!$C:$C, Sheet1!$E:$E), "")
A15: Janapriya Jeganathan | B15: Operations Analyst | C15: Greensky® | D15: 1+ | E15: SQL | F15: C (Programming Language) | G15: https://www.linkedin.com/in/janapriya-jeganathan | H15: Austin | I15: Texas | J15: United States | L15: =IFERROR(_xlfn.XLOOKUP(TRIM(G15), Sheet1!$C:$C, Sheet1!$E:$E), "")
A16: Sravya Jahagirdar | B16: Technical Product Owner | C16: Autozone | D16: 1 | E16: WMS | F16: Supply Chain Operations | G16: https://www.linkedin.com/in/sravyajahagirdar | H16: New York City Metropolitan Area | I16: New York | J16: United States | L16: =IFERROR(_xlfn.XLOOKUP(TRIM(G16), Sheet1!$C:$C, Sheet1!$E:$E), "")
A17: Damien Gombert | B17: Quality Assurance Engineer | C17: Bently Nevada, A Baker Hughes Business | D17: 6+ | E17: Tableau | F17: Quality Management | G17: https://www.linkedin.com/in/damiengombert | H17: Greater Reno Area | I17: vijay72prince@gmail.com | J17: United States | L17: =IFERROR(_xlfn.XLOOKUP(TRIM(G17), Sheet1!$C:$C, Sheet1!$E:$E), "")
A18: Richard Troscianecki | B18: Real Estate Agent | C18: Century 21 Select Group | D18: 4+ | E18: EMC Documentum | F18: Pega PRPC | G18: https://www.linkedin.com/in/richardtroscianecki | H18: Gouldsboro | I18: North Carolina | J18: United States | L18: =IFERROR(_xlfn.XLOOKUP(TRIM(G18), Sheet1!$C:$C, Sheet1!$E:$E), "")
A19: Jessima Aiman | B19: Manager - Business Development | C19: Oneorigin | D19: 1+ | E19: Business Development | F19: Management | G19: https://www.linkedin.com/in/jessima-aiman | H19: Scottsdale | I19: California | J19: United States | L19: =IFERROR(_xlfn.XLOOKUP(TRIM(G19), Sheet1!$C:$C, Sheet1!$E:$E), "")
A20: Aditya Pujari | B20: Sr consultant | C20: Ey | D20: 0.4 | E20: Timelines | F20: Scorecard | G20: https://www.linkedin.com/in/adityapujari777 | H20: Mumbai | I20: Michigan | J20: India | L20: =IFERROR(_xlfn.XLOOKUP(TRIM(G20), Sheet1!$C:$C, Sheet1!$E:$E), "")
A21: Md Ahmed Ali | B21: Sr. Bench Sales Recruiter | C21: Career Soft Solutions Inc | D21: 1+ | E21: Screening Resumes | G21: https://www.linkedin.com/in/mohammed-recruiter | H21: New York City Metropolitan Area | I21: New York | J21: United States | L21: =IFERROR(_xlfn.XLOOKUP(TRIM(G21), Sheet1!$C:$C, Sheet1!$E:$E), "")
A22: Sangeetha Jayakrishnan | B22: Practice Manager | D22: 2+ | E22: Records Management | F22: leadership | G22: https://www.linkedin.com/in/sangeethajayakrishnan | H22: Livermore | I22: Haryana | J22: United States | L22: =IFERROR(_xlfn.XLOOKUP(TRIM(G22), Sheet1!$C:$C, Sheet1!$E:$E), "")
A23: Ganesan V | B23: Performance Marketing Consultant | D23: 0.3 | E23: YouTube | F23: Google Ads | G23: https://www.linkedin.com/in/ganesan-v | H23: Tamil Nadu | I23: India | L23: =IFERROR(_xlfn.XLOOKUP(TRIM(G23), Sheet1!$C:$C, Sheet1!$E:$E), "")
A24: Madhumitha Rajesh | B24: User Experience Intern | C24: Playerapp | D24: 0.3 | E24: AI-Powered Research Tools | F24: Data Analysis | G24: https://www.linkedin.com/in/madhumitha-rajesh-76078018a | H24: Greater Seattle Area | I24: Washington | J24: United States | L24: =IFERROR(_xlfn.XLOOKUP(TRIM(G24), Sheet1!$C:$C, Sheet1!$E:$E), "")
A25: Amit Trivedi | B25: Staffing Consultant | C25: Confidential | D25: 1+ | E25: Staffing Industry | F25: Sales | G25: https://www.linkedin.com/in/amit-trivedi-9aa42b14 | H25: India | I25: India | J25: United States | L25: =IFERROR(_xlfn.XLOOKUP(TRIM(G25), Sheet1!$C:$C, Sheet1!$E:$E), "")
A26: MANOJ BAKSHI | B26: PRINTING | G26: https://www.linkedin.com/in/manoj-bakshi-24178a1b | H26: Noida | I26: Telangana | J26: India | L26: =IFERROR(_xlfn.XLOOKUP(TRIM(G26), Sheet1!$C:$C, Sheet1!$E:$E), "")
A27: Anson Mathew | B27: Team Lead | D27: 9+ | E27: SDLC | F27: XML | G27: https://www.linkedin.com/in/anson-mathew-a8ab4465 | H27: Olathe | I27: Missouri | J27: United States | L27: =IFERROR(_xlfn.XLOOKUP(TRIM(G27), Sheet1!$C:$C, Sheet1!$E:$E), "")
A28: Dinesh Kumar Rajendran | B28: Director- Head of Sales | C28: Highbrow Technology Inc | D28: 2+ | E28: Business Integration | F28: Partnership & Relationship Building | G28: https://www.linkedin.com/in/dinesh-kumar-rajendran | H28: Morrisville | I28: Bihar | J28: United States | L28: =IFERROR(_xlfn.XLOOKUP(TRIM(G28), Sheet1!$C:$C, Sheet1!$E:$E), "")
A29: Swetha Ragothaman | B29: Program Manager | C29: Zero Rideshare | D29: 1+ | E29: Zoho CRM | F29: Functional Testing | G29: https://www.linkedin.com/in/swetha-ragothaman | H29: San Francisco Bay Area | I29: California | J29: United States | L29: =IFERROR(_xlfn.XLOOKUP(TRIM(G29), Sheet1!$C:$C, Sheet1!$E:$E), "")
A30: Calvin Dcosta | B30: NetSuite Functional Consultant - Configurations | C30: Zenardy | D30: 1+ | E30: NetSuite ERP Configurations & Customization | F30: Data Visualization & Reporting | G30: https://www.linkedin.com/in/calvin-dcosta | H30: Mumbai | I30: Michigan | J30: India | L30: =IFERROR(_xlfn.XLOOKUP(TRIM(G30), Sheet1!$C:$C, Sheet1!$E:$E), "")
A31: Tamilarasan S | B31: Suppy Chain and Delivery Manager | C31: Natwest Group | D31: 2+ | E31: Microsoft Copilot Studio | F31: Agile Methodologies | G31: https://www.linkedin.com/in/tamizh1 | H31: Chennai | I31: India | J31: India | L31: =IFERROR(_xlfn.XLOOKUP(TRIM(G31), Sheet1!$C:$C, Sheet1!$E:$E), "")
A32: Amol Khugshal | B32: Senior Product Manager | C32: Miniclip | D32: 0.6 | E32: Monetization | F32: User Research | G32: https://www.linkedin.com/in/amol-khugshal | H32: Portugal | L32: =IFERROR(_xlfn.XLOOKUP(TRIM(G32), Sheet1!$C:$C, Sheet1!$E:$E), "")
A33: Elma Mathew | B33: Registered Nurse | C33: Pine Valley Center For Rehabilitation | D33: 1+ | E33: Data Analysis | F33: Customer Service | G33: https://www.linkedin.com/in/elma-mathew-3970361b9 | H33: West Haverstraw | I33: Karnataka | J33: United States | L33: =IFERROR(_xlfn.XLOOKUP(TRIM(G33), Sheet1!$C:$C, Sheet1!$E:$E), "")
A34: Prasanna Balachandran | B34: Technical Delivery Manager | C34: Ey | D34: 8+ | E34: Fieldglass | F34: Product Owner | G34: https://www.linkedin.com/in/prasanna-balachandran-cloud-enthusiast | H34: Metro Jacksonville | I34: Prasanna2567@gmail.com | L34: =IFERROR(_xlfn.XLOOKUP(TRIM(G34), Sheet1!$C:$C, Sheet1!$E:$E), "")
A35: veeramani subramaniam | B35: Manager | C35: Cognizant | D35: 3+ | E35: PL/SQL | F35: Oracle | G35: https://www.linkedin.com/in/veeramani-subramaniam-9271a77 | H35: Raleigh-Durham-Chapel Hill Area | I35: North Carolina | L35: =IFERROR(_xlfn.XLOOKUP(TRIM(G35), Sheet1!$C:$C, Sheet1!$E:$E), "")
A36: Anshul . | B36: AVP-Operations | C36: Echelon Edge | D36: 0.8 | E36: Sales Processes | F36: Sales | G36: https://www.linkedin.com/in/anshul-90a80988 | H36: Gurugram | I36: Pakistan | J36: India | L36: =IFERROR(_xlfn.XLOOKUP(TRIM(G36), Sheet1!$C:$C, Sheet1!$E:$E), "")
A37: CHIBWE CHUNGU | B37: Americas Operations Lead Vegetables Seeds Development | C37: Syngenta | D37: 1+ | E37: Speaking | F37: Facilitation | G37: https://www.linkedin.com/in/chibwe-chungu1997 | H37: Galt | I37: Haryana | J37: United States | L37: =IFERROR(_xlfn.XLOOKUP(TRIM(G37), Sheet1!$C:$C, Sheet1!$E:$E), "")
A38: Ranganath P. | B38: Validation Lead | C38: Genentech | D38: 11+ | E38: U.S. Title 21 CFR Part 11 Regulation | F38: Change Control | G38: https://www.linkedin.com/in/ranganath-p-a41391149 | H38: Fremont | I38: Haryana | J38: United States | L38: =IFERROR(_xlfn.XLOOKUP(TRIM(G38), Sheet1!$C:$C, Sheet1!$E:$E), "")
A39: Keerthana Nagula | B39: Business Intelligence Engineer | C39: Impetus | D39: 1+ | E39: Requirements Analysis | F39: Business Requirements | G39: https://www.linkedin.com/in/keerthana-nagula | H39: Bengaluru | I39: Bahrain | J39: India | L39: =IFERROR(_xlfn.XLOOKUP(TRIM(G39), Sheet1!$C:$C, Sheet1!$E:$E), "")
A40: Madhu Gupta | B40: Personal Branding & Ghostwriting | D40: 4+ | E40: Social Media | F40: Marketing Strategy | G40: https://www.linkedin.com/in/madhudigitalmarketer | H40: Mumbai | I40: Michigan | J40: India | L40: =IFERROR(_xlfn.XLOOKUP(TRIM(G40), Sheet1!$C:$C, Sheet1!$E:$E), "")
A41: Harshini Bala | B41: Human Resources Coordinator | C41: The Little Nell | D41: 0.3 | E41: Customer Relationship Management (CRM) | F41: Workday HRM | G41: https://www.linkedin.com/in/harshini-bala-21490720b | H41: Aspen | I41: Australia | J41: United States | L41: =IFERROR(_xlfn.XLOOKUP(TRIM(G41), Sheet1!$C:$C, Sheet1!$E:$E), "")
A42: Irene M. | B42: Human Resources Director | D42: 6 | E42: HR Consulting | F42: Human Resource Development | G42: https://www.linkedin.com/in/irenemiora | H42: Mumbai Metropolitan Region | I42: Maharashtra | J42: India | L42: =IFERROR(_xlfn.XLOOKUP(TRIM(G42), Sheet1!$C:$C, Sheet1!$E:$E), "")
A43: Tahira Taj | B43: Accountant | C43: Nurulquran | D43: 10+ | E43: Vendor Management | F43: Nonprofit Organizations | G43: https://www.linkedin.com/in/tahira-taj-9a430764 | H43: Lahore | I43: Finland | J43: Pakistan | L43: =IFERROR(_xlfn.XLOOKUP(TRIM(G43), Sheet1!$C:$C, Sheet1!$E:$E), "")
A44: Pankaj Jaiswal | B44: Forward Deployed AI Engineer | C44: Supervity | D44: 0.7 | E44: Engineering Design | F44: Logical Approach | G44: https://www.linkedin.com/in/pankaj29 | H44: Mumbai | I44: Michigan | J44: India | L44: =IFERROR(_xlfn.XLOOKUP(TRIM(G44), Sheet1!$C:$C, Sheet1!$E:$E), "")
A45: Pramit Gopal Yeole | B45: Senior Engineer | C45: Pwc | D45: 0.6 | E45: AI Agents | F45: Kubernetes | G45: https://www.linkedin.com/in/pramit-yeole | H45: San Francisco | I45: Haryana | J45: United States | L45: =IFERROR(_xlfn.XLOOKUP(TRIM(G45), Sheet1!$C:$C, Sheet1!$E:$E), "")
A46: VIJAY KUMAR SHARMA Funds Raising/Revenue Generation | B46: Founder | C46: It-Startup | D46: 2 | E46: Business Development | F46: Business Process Improvement | G46: https://www.linkedin.com/in/vijay-kumar-sharma-funds-raising-revenue-generation-89487314b | H46: South Delhi | I46: Nepal | J46: India | L46: =IFERROR(_xlfn.XLOOKUP(TRIM(G46), Sheet1!$C:$C, Sheet1!$E:$E), "")
A47: Vaidiyanathan Lalgudi Venkatesan | B47: Data scientist II | C47: Amazon | D47: 6 | E47: Artificial Intelligence (AI) | F47: Decision Sciences | G47: https://www.linkedin.com/in/vaidiyanathanlv | H47: Chennai | I47: India | J47: India | L47: =IFERROR(_xlfn.XLOOKUP(TRIM(G47), Sheet1!$C:$C, Sheet1!$E:$E), "")
A48: Sarika Tyagi | B48: Content Lead | C48: Spinny | D48: 2+ | E48: Clarity | F48: Proofreading | G48: https://www.linkedin.com/in/sarika-tyagi-5577a23b | H48: New Delhi | I48: Nepal | J48: India | L48: =IFERROR(_xlfn.XLOOKUP(TRIM(G48), Sheet1!$C:$C, Sheet1!$E:$E), "")
A49: Amrita Chafekar Chikhalkar | B49: Product Specialist - Information Technology | C49: Blink Charging | D49: 3+ | E49: Product Lifecycle Management | F49: Regulatory Compliance | G49: https://www.linkedin.com/in/amrita-chafekar-chikhalkar-45883315a | H49: San Francisco Bay Area | I49: California | J49: United States | L49: =IFERROR(_xlfn.XLOOKUP(TRIM(G49), Sheet1!$C:$C, Sheet1!$E:$E), "")
A50: Darrell Cromer | B50: Help Desk Technician | C50: Trace Systems Inc. | D50: 3+ | E50: Customer Service | F50: Public Speaking | G50: https://www.linkedin.com/in/darrell-cromer-62373634 | H50: Kuwait | L50: =IFERROR(_xlfn.XLOOKUP(TRIM(G50), Sheet1!$C:$C, Sheet1!$E:$E), "")
A51: Mohamed Almedfa | B51: Lecturer - Internal Medicine Department | C51: Arabian Gulf University | D51: 1+ | G51: https://www.linkedin.com/in/mohamed-almedfa | H51: Riffa | I51: China | J51: Bahrain | L51: =IFERROR(_xlfn.XLOOKUP(TRIM(G51), Sheet1!$C:$C, Sheet1!$E:$E), "")
A52: Aditya Middha | B52: Product Manager II | C52: Microsoft | D52: 1+ | E52: Project Management | F52: Programming | G52: https://www.linkedin.com/in/aditya-middha | H52: Greater Seattle Area | I52: Washington | J52: United States | L52: =IFERROR(_xlfn.XLOOKUP(TRIM(G52), Sheet1!$C:$C, Sheet1!$E:$E), "")
A53: harneet boparai | C53: Boparai Associates | G53: https://www.linkedin.com/in/harneet-boparai-749072344 | H53: Fresno | I53: Haryana | J53: United States | L53: =IFERROR(_xlfn.XLOOKUP(TRIM(G53), Sheet1!$C:$C, Sheet1!$E:$E), "")
A54: Adesh Oswal | B54: Product Support Specialist | C54: Regrow Ag | D54: 1+ | E54: HubSpot | F54: Jira | G54: https://www.linkedin.com/in/adeshoswal | H54: Hacienda Heights | I54: Haryana | J54: United States | L54: =IFERROR(_xlfn.XLOOKUP(TRIM(G54), Sheet1!$C:$C, Sheet1!$E:$E), "")
A55: Ralph Munashe Moyo | B55: Heavy Diesel Mechanic | C55: Mcintosh & Son | D55: 2+ | E55: Technical Drawing | F55: HD Mechanic | G55: https://www.linkedin.com/in/ralph-munashe-moyo-22172487 | H55: St Ruth | I55: Spain | J55: Australia | L55: =IFERROR(_xlfn.XLOOKUP(TRIM(G55), Sheet1!$C:$C, Sheet1!$E:$E), "")
A56: Mohammed Ashfaq Ahmed | B56: Data Analyst | C56: Elite Group Holding | D56: 0.8 | E56: Exploratory Data Analysis | F56: Data Modeling | G56: https://www.linkedin.com/in/mohdashfaqahmed | H56: Dubai | I56: Burkina Faso | L56: =IFERROR(_xlfn.XLOOKUP(TRIM(G56), Sheet1!$C:$C, Sheet1!$E:$E), "")
A57: Dhurba kunwar | B57: Logistics Executive | C57: Sol HenkilöStöPalvelut Oy | D57: 2+ | E57: Team Management | F57: Customer Service | G57: https://www.linkedin.com/in/dhurba-kunwar-b2745793 | H57: Turku | I57: Egypt | J57: Finland | L57: =IFERROR(_xlfn.XLOOKUP(TRIM(G57), Sheet1!$C:$C, Sheet1!$E:$E), "")
A58: Shubham Jain | B58: Senior Executive | C58: Prologis Freight | D58: 0.9 | E58: Export Documentation | F58: Import Export | G58: https://www.linkedin.com/in/shubham-jain1996 | H58: Gautam Buddha Nagar | I58: Telangana | J58: India | L58: =IFERROR(_xlfn.XLOOKUP(TRIM(G58), Sheet1!$C:$C, Sheet1!$E:$E), "")
A59: Jinesha Jain | B59: Senior Data Analyst | C59: Realtor.Com | D59: 1+ | E59: KPI Reporting | F59: Business Process Improvement | G59: https://www.linkedin.com/in/jineshajain | H59: Austin | I59: Ireland | L59: =IFERROR(_xlfn.XLOOKUP(TRIM(G59), Sheet1!$C:$C, Sheet1!$E:$E), "")
A60: Simarjot Khangura | B60: Business Owner | D60: 5+ | E60: Spanish-speaking | F60: Microsoft PowerPoint | G60: https://www.linkedin.com/in/simarjot-khangura | H60: San Ramon | I60: Haryana | J60: United States | L60: =IFERROR(_xlfn.XLOOKUP(TRIM(G60), Sheet1!$C:$C, Sheet1!$E:$E), "")
A61: Parag Baldha | B61: Field Technician | C61: Parklandgeo Ltd. | D61: 0.8 | E61: Critical Thinking | F61: Interpersonal Skills | G61: https://www.linkedin.com/in/parag-baldha | H61: Calgary | I61: North Macedonia | J61: Canada | L61: =IFERROR(_xlfn.XLOOKUP(TRIM(G61), Sheet1!$C:$C, Sheet1!$E:$E), "")
A62: Tamanna Kakkar | B62: Technical Communications Specialist | D62: 0.8 | E62: Corporate Communications | F62: Microsoft 365 | G62: https://www.linkedin.com/in/tamanna-kakkar | H62: Austin | I62: Ireland | L62: =IFERROR(_xlfn.XLOOKUP(TRIM(G62), Sheet1!$C:$C, Sheet1!$E:$E), "")
A63: venkata subba reddy kuncham | B63: Senior Data Engineer | C63: Info Services | D63: 1+ | E63: Cloud Services | F63: Design and implement data storage | G63: https://www.linkedin.com/in/venkata-subba-reddy-kuncham-a2507263 | H63: Detroit Metropolitan Area | I63: Michigan | L63: =IFERROR(_xlfn.XLOOKUP(TRIM(G63), Sheet1!$C:$C, Sheet1!$E:$E), "")
A64: Suraksha Sharma | B64: Accountant | D64: 2+ | E64: Bank Reconciliation | F64: Financial Statements | G64: https://www.linkedin.com/in/suraksha-sharma-82563310b | H64: Darjeeling | I64: Denmark | J64: India | L64: =IFERROR(_xlfn.XLOOKUP(TRIM(G64), Sheet1!$C:$C, Sheet1!$E:$E), "")
A65: Prasanna Reddy | B65: DevSecOps Fullstack Security Engineer | C65: Standard Chartered | D65: 1+ | E65: Ffmpeg | F65: nodejs | G65: https://www.linkedin.com/in/prasanna3000 | H65: Chennai | I65: India | J65: India | L65: =IFERROR(_xlfn.XLOOKUP(TRIM(G65), Sheet1!$C:$C, Sheet1!$E:$E), "")
A66: Keshav Jindal | B66: Member of Technical Staff 2 | C66: Nutanix | D66: 0.7 | E66: OpenAPI Specification (OAS) | F66: OData | G66: https://www.linkedin.com/in/keshavjindal555 | H66: United States | I66: United States | J66: United States | L66: =IFERROR(_xlfn.XLOOKUP(TRIM(G66), Sheet1!$C:$C, Sheet1!$E:$E), "")
A67: Manpreet Singh | B67: Welder-Fitter | C67: Ami Attachments® | D67: 1+ | E67: Jigs | F67: Gauging | G67: https://www.linkedin.com/in/manna88107 | H67: Brampton | I67: Japan | J67: Canada | L67: =IFERROR(_xlfn.XLOOKUP(TRIM(G67), Sheet1!$C:$C, Sheet1!$E:$E), "")
A68: Kate True | B68: Founder Business English Centre | C68: The Business English Centre Ltd | D68: 7+ | E68: Spanish (bi-lingual), good German and Italian, a little Turkish | F68: Coaching | G68: https://www.linkedin.com/in/kate-true-a6133421 | H68: N/A | I68: N/A | J68: N/A | L68: =IFERROR(_xlfn.XLOOKUP(TRIM(G68), Sheet1!$C:$C, Sheet1!$E:$E), "")
A69: Sonakshi Senthil | B69: Co-Founder | C69: Your Cue | D69: 4+ | E69: Quality Patient Care | F69: Personalised Medicine | G69: https://www.linkedin.com/in/sonakshisenthil | H69: London Area | I69: United Kingdom | L69: =IFERROR(_xlfn.XLOOKUP(TRIM(G69), Sheet1!$C:$C, Sheet1!$E:$E), "")
A70: Vimmy M. | B70: Senior Manager of Product Management | C70: Wesco | D70: 2+ | E70: Artificial Intelligence (AI) | F70: E-Commerce | G70: https://www.linkedin.com/in/vimmymodi | H70: Dallas | I70: Texas | J70: United States | L70: =IFERROR(_xlfn.XLOOKUP(TRIM(G70), Sheet1!$C:$C, Sheet1!$E:$E), "")
A71: AMAN TRIVEDI | B71: Assistant | D71: 4+ | E71: English | F71: Research | G71: https://www.linkedin.com/in/aman-trivedi | H71: Howrah | I71: Denmark | J71: India | L71: =IFERROR(_xlfn.XLOOKUP(TRIM(G71), Sheet1!$C:$C, Sheet1!$E:$E), "")
A72: Harsh Josan | B72: Mortgage Loan Officer | D72: 1+ | E72: Conventional Financing | F72: U.S. VA Loans | G72: https://www.linkedin.com/in/harshjosan | H72: Greater Indianapolis | L72: =IFERROR(_xlfn.XLOOKUP(TRIM(G72), Sheet1!$C:$C, Sheet1!$E:$E), "")
A73: Jaspreet Singh | B73: Analyst | C73: Apollo Global Management, Inc. | D73: 0.8 | E73: Pinia | F73: AngularJS | G73: https://www.linkedin.com/in/7-singh-jp | H73: Mumbai | I73: Michigan | J73: India | L73: =IFERROR(_xlfn.XLOOKUP(TRIM(G73), Sheet1!$C:$C, Sheet1!$E:$E), "")
A74: Sarthak Jain, MSc | B74: Research Analyst | C74: Villanova University | D74: 0.9 | E74: Data Visualization | F74: Excel | G74: https://www.linkedin.com/in/sarthak-jainsj | H74: Greater Philadelphia | L74: =IFERROR(_xlfn.XLOOKUP(TRIM(G74), Sheet1!$C:$C, Sheet1!$E:$E), "")
A75: Abhyas Ramadugu | B75: Growth Marketer | C75: Remitly | D75: 0.3 | E75: WordPress | F75: Adobe Analytics | G75: https://www.linkedin.com/in/abhyas-r | H75: Seattle | I75: Sudan | J75: United States | L75: =IFERROR(_xlfn.XLOOKUP(TRIM(G75), Sheet1!$C:$C, Sheet1!$E:$E), "")
A76: Lawerence Ortiz | B76: Construction Laborer | G76: https://www.linkedin.com/in/lawerence-ortiz-834a9a120 | H76: Greater Seattle Area | I76: Washington | J76: United States | L76: =IFERROR(_xlfn.XLOOKUP(TRIM(G76), Sheet1!$C:$C, Sheet1!$E:$E), "")
A77: Puranjit Singh | B77: Data Science Co-op | C77: Bayer | D77: 0.1 | E77: Python (Programming Language) | F77: Machine Learning | G77: https://www.linkedin.com/in/puranjit-singh-94303813a | H77: Ankeny | I77: Uganda | J77: United States | L77: =IFERROR(_xlfn.XLOOKUP(TRIM(G77), Sheet1!$C:$C, Sheet1!$E:$E), "")
A78: Bhavya Jain | B78: Human Resources Intern | C78: _vois | D78: 0.2 | E78: Research Projects | F78: Data Visualization | G78: https://www.linkedin.com/in/bhavyajain8306 | H78: Pune | I78: Michigan | J78: India | L78: =IFERROR(_xlfn.XLOOKUP(TRIM(G78), Sheet1!$C:$C, Sheet1!$E:$E), "")
A79: Vishaldeep Singh | B79: Trading Operations Specialist | C79: Own Bussiness | D79: 0.8 | E79: Cryptos | F79: Stocks | G79: https://www.linkedin.com/in/vishaldeep-singh-570597104 | H79: Ludhiana | I79: Finland | J79: India | L79: =IFERROR(_xlfn.XLOOKUP(TRIM(G79), Sheet1!$C:$C, Sheet1!$E:$E), "")
A80: Prathamesh Chopade | B80: Assistant Research Scientist | C80: Asu Biodesign Institute | D80: 3+ | E80: Spectroscopy | F80: Nanotechnology | G80: https://www.linkedin.com/in/pratham4292 | H80: Tempe | I80: California | J80: United States | L80: =IFERROR(_xlfn.XLOOKUP(TRIM(G80), Sheet1!$C:$C, Sheet1!$E:$E), "")
A81: Luna Mia | B81: Self Employed | E81: Government | G81: https://www.linkedin.com/in/luna-mia-763a201bb | H81: Palmdale | I81: Haryana | J81: United States | L81: =IFERROR(_xlfn.XLOOKUP(TRIM(G81), Sheet1!$C:$C, Sheet1!$E:$E), "")
A82: Riya Dhall | B82: Associate | C82: Goldman Sachs | D82: 0.5 | E82: Social Media | F82: Microsoft Office | G82: https://www.linkedin.com/in/riya-dhall-a7325913b | H82: New York | I82: Karnataka | J82: United States | L82: =IFERROR(_xlfn.XLOOKUP(TRIM(G82), Sheet1!$C:$C, Sheet1!$E:$E), "")
A83: Navreet Suri | B83: Postdoctoral Researcher | C83: University Of Alberta | D83: 1+ | E83: Microbiology | F83: Laboratory Skills | G83: https://www.linkedin.com/in/navreet-suri | H83: United Kingdom | I83: United Kingdom | J83: United Kingdom | L83: =IFERROR(_xlfn.XLOOKUP(TRIM(G83), Sheet1!$C:$C, Sheet1!$E:$E), "")
A84: Lexi Tiroff | B84: Neonatal Intensive Care Nurse | C84: St. David'S Healthcare | D84: 5 | E84: Leadership | F84: Time Management | G84: https://www.linkedin.com/in/lexi-tiroff | H84: Austin | I84: Texas | J84: United States | L84: =IFERROR(_xlfn.XLOOKUP(TRIM(G84), Sheet1!$C:$C, Sheet1!$E:$E), "")
A85: Amrit Pal, PhD | B85: Sr Supervisor HACCP | C85: Tyson Foods | D85: 0.8 | E85: Fresh Produce | F85: Experimental Design | G85: https://www.linkedin.com/in/amrit-pal-food-scientist | H85: Sedalia | I85: Sweden | J85: United States | L85: =IFERROR(_xlfn.XLOOKUP(TRIM(G85), Sheet1!$C:$C, Sheet1!$E:$E), "")
A86: Gurninder Kaur | B86: Front Desk Staff | D86: 2+ | E86: Customer Service Representatives | F86: Customer Experience | G86: https://www.linkedin.com/in/gurninder-kaur-a2851a22b | H86: United States | I86: United States | J86: United States | L86: =IFERROR(_xlfn.XLOOKUP(TRIM(G86), Sheet1!$C:$C, Sheet1!$E:$E), "")
A87: Sukhbir Brar | B87: Accountant | C87: Fresno Madera Farm Credit | D87: 0.7 | E87: Nonprofit Organizations | F87: Year-End Accounting | G87: https://www.linkedin.com/in/sukhbirbrar | H87: Fresno | I87: Haryana | J87: United States | L87: =IFERROR(_xlfn.XLOOKUP(TRIM(G87), Sheet1!$C:$C, Sheet1!$E:$E), "")
A88: Hardeep Gujral | B88: Airport Duty Manager | C88: British Airways | D88: 4+ | E88: Liaison Between Departments | F88: Concierge Services | G88: https://www.linkedin.com/in/hardeep-gujral-7b90954 | H88: New York | I88: Karnataka | J88: United States | L88: =IFERROR(_xlfn.XLOOKUP(TRIM(G88), Sheet1!$C:$C, Sheet1!$E:$E), "")
A89: Avtar Basra | B89: Network Support Engineer | C89: Ericsson | D89: 7+ | E89: IP | F89: Integration | G89: https://www.linkedin.com/in/avtarbasra | H89: Hayward | I89: Haryana | J89: United States | L89: =IFERROR(_xlfn.XLOOKUP(TRIM(G89), Sheet1!$C:$C, Sheet1!$E:$E), "")
A90: Ayush Anchal | B90: Technology Analyst | C90: Edgeverve | D90: 3+ | E90: Responsible AI | F90: NumPy | G90: https://www.linkedin.com/in/ayush-anchal | H90: Bengaluru | I90: Bahrain | J90: India | L90: =IFERROR(_xlfn.XLOOKUP(TRIM(G90), Sheet1!$C:$C, Sheet1!$E:$E), "")
A91: Gurpreet Mahal | B91: General Practitioner | D91: 3+ | E91: Internal Medicine | F91: Non-invasive Cardiology | G91: https://www.linkedin.com/in/gurpreet-mahal | H91: Adelaide | I91: France | J91: Australia | L91: =IFERROR(_xlfn.XLOOKUP(TRIM(G91), Sheet1!$C:$C, Sheet1!$E:$E), "")
A92: Geetika Ghai | B92: Assistant General Manager | C92: Marriott International | D92: 1+ | E92: Opening Hotels | F92: Guest Service Management | G92: https://www.linkedin.com/in/geetika-ghai-a48549131 | H92: Westbury | I92: Karnataka | J92: United States | L92: =IFERROR(_xlfn.XLOOKUP(TRIM(G92), Sheet1!$C:$C, Sheet1!$E:$E), "")
A93: Aamina Farooq | B93: Business Analyst I | C93: Td | D93: 0.6 | E93: Business Analysis | F93: Data Analysis | G93: https://www.linkedin.com/in/aamina-farooq | H93: Philadelphia | I93: North Carolina | J93: United States | L93: =IFERROR(_xlfn.XLOOKUP(TRIM(G93), Sheet1!$C:$C, Sheet1!$E:$E), "")
A94: Rajinder Taneja | B94: Executive Assistant | C94: Todaystrends Ltd | D94: 18+ | E94: Business Analysis | F94: Financial Accounting | G94: https://www.linkedin.com/in/rajinder-taneja-b6640091 | H94: United States | I94: United States | J94: United States | L94: =IFERROR(_xlfn.XLOOKUP(TRIM(G94), Sheet1!$C:$C, Sheet1!$E:$E), "")
A95: Ram Adhar | B95: Head - Digital Marketing | C95: Digivigyan: Digital Marketing Agency India | D95: 1+ | E95: SEO Services | F95: SEO Expert | G95: https://www.linkedin.com/in/trydigitalram | H95: Delhi | I95: India | L95: =IFERROR(_xlfn.XLOOKUP(TRIM(G95), Sheet1!$C:$C, Sheet1!$E:$E), "")
A96: Aradhya Garg | B96: Investment Banking Summer Analyst | C96: Citi | D96: 0.9 | E96: R (Programming Language) | F96: Python (Programming Language) | G96: https://www.linkedin.com/in/aradhya-garg-9a4138200 | H96: Greater Boston | L96: =IFERROR(_xlfn.XLOOKUP(TRIM(G96), Sheet1!$C:$C, Sheet1!$E:$E), "")
A97: Sresth Gupta | B97: Summer Analyst | C97: Knollwood Investment Advisory | D97: 0.8 | E97: Strategic Planning | F97: Impact Investing | G97: https://www.linkedin.com/in/sresth-gupta | H97: New York City Metropolitan Area | I97: New York | J97: United States | L97: =IFERROR(_xlfn.XLOOKUP(TRIM(G97), Sheet1!$C:$C, Sheet1!$E:$E), "")
A98: Vedant Athavale | B98: Product Operations Manager | C98: Curafitt | D98: 0.8 | E98: Lean Six Sigma | F98: Six Sigma Green Belt | G98: https://www.linkedin.com/in/vedant-athavale | H98: United States | I98: United States | J98: United States | L98: =IFERROR(_xlfn.XLOOKUP(TRIM(G98), Sheet1!$C:$C, Sheet1!$E:$E), "")
A99: Mandeep Thukral | B99: Senior Vice President - Asset Management | C99: Profrac Services | D99: 1+ | E99: Logistics | F99: Frac sand | G99: https://www.linkedin.com/in/mandeep-thukral | H99: Houston | I99: Texas | J99: United States | L99: =IFERROR(_xlfn.XLOOKUP(TRIM(G99), Sheet1!$C:$C, Sheet1!$E:$E), "")
A100: Sambhav Upadhyay | B100: Limited Partner (Founder) | C100: Iceberg Sports Advisory | D100: 2+ | G100: https://www.linkedin.com/in/sambhavu | H100: New York City Metropolitan Area | I100: New York | J100: United States | L100: =IFERROR(_xlfn.XLOOKUP(TRIM(G100), Sheet1!$C:$C, Sheet1!$E:$E), "")
...

Sheet Sheet1
A1: Designation | B1: Location | C1: Linkedin Url | D1: raw text | E1: Email
A2: Instrumentation Design Engineer | B2: Haryana | C2: https://www.linkedin.com/in/eashangsingh | D2: Eashan Singh - New York, New York, United States .singh1@gmail.com. I look forward to speaking with you! · Experience ... Software Engineering Intern. Google. May 2023 - Aug 2023 4 ... | E2: .singh1@gmail.com
A3: Chat Support Executive | B3: Aurangabad | C3: https://www.linkedin.com/in/ananyayadav | D3: Ananya Yadav - New York City Metropolitan Area ... chat about data, innovation, or books, let's connect! Reach me at 06ananyayadav06@gmail.com ... executives. Optimizing Supply Chain Operations with Data ... | E3: 06ananyayadav06@gmail.com
A4: Civil Quality Engineer | B4: Meerut | C4: https://www.linkedin.com/in/hritik-garg-249905163/ | D4: Hritik Garg - Associate SDET - Taazaa Inc Version control wiz using GitHub for collaborative coding. Eager to connect and grow. Let's chat: 13hritik@gmail.com or right here on LinkedIn. | E4: 13hritik@gmail.com
A5: Email Support Executive | B5: Jodhpur | C5: https://www.linkedin.com/in/jayeshkumarpatel-41839621 | D5: JAYESH KUMAR PATEL - General Manager ... email me at 1972.patel@gmail.com · Experience: General Manager at Joshi Technologeis Intl Inc · Education: B.Sc. from J&J College of Science-Gujarat ... | E5: 1972.patel@gmail.com
A6: Email Support Executive | B6: Agra | C6: https://www.linkedin.com/in/kazhall | D6: Karen Hall - Mindfulness Retreat Leader - Way of ... ... email me at 1kazhall@gmail.com. Articles by Karen. Kerala, January 2024 ... Business Support Manager 0121 466 7544. Email: eileen.brennan@bhamcommunity ... | E6: 1kazhall@gmail.com
A7: Light Vehicle Driver | B7: Andhra Pradesh | C7: https://www.linkedin.com/in/troy-hanson- | D7: Troy Hanson - Race Team Manager - Principle Engineer ... Automotive Engineering ▻ Contact: 1tj.hanson@gmail.com · Experience: Honda Performance Development · Education: Madison Area Technical College · Location ... | E7: 1tj.hanson@gmail.com
A8: Commercial Executive | B8: Rajkot | C8: https://www.linkedin.com/in/themehulpatil | D8: Mehul Patil - Sr. Executive Digital Marketing - KP Group ✉️ Email me at mehulpatil@273@gmail.com. Services. Blogging · Market Research · Content Strategy · Digital Marketing · Content Marketing · Search Engine ... | E8: 273@gmail.com
A9: Sales Representative | B9: Vadodara | C9: https://www.linkedin.com/in/jamespoole0in0raleighnc | D9: James L Poole - Duke Energy Corporation 400emerson@gmail.com / 919 621-0891 (mobile) Technical Professional with proven… · Experience: Duke Energy Corporation · Education: North Carolina State ... | E9: 400emerson@gmail.com
A10: Document Verification Executive | B10: Andhra Pradesh | C10: https://www.linkedin.com/in/yifanyang25 | D10: Yifan Yang - Salesforce Functional Analyst - Sysco • Handled DHL's Sanity Check Tool to check and correct all the potential errors before the quotation submission ... Credential ID 7yyang7@gmail.com. See ... | E10: 7yyang7@gmail.com
A11: Technician | B11: Andhra Pradesh | C11: https://www.linkedin.com/in/carlene-artist-a384a776 | D11: Carlene Artist - District Supervisor - Survey.com We are currently taking applications for students,simply send us a email to 8counts2dance@gmail.com and we will get a application form to you as soon as ... | E11: 8counts2dance@gmail.com
A12: Industrial safety officer | B12: Andhra Pradesh | C12: https://www.linkedin.com/in/a-lake-wooten | D12: Andrew Lake Wooten - Purdue University College of ... a.lake.wooten@gmail.com • 12 years in radiopharmaceuticals and medical isotopes with… · Experience: Purdue University College of Pharmacy · Education: ... | E12: a.lake.wooten@gmail.com
... A2434: Courier Executive | B2434: Bihar | C2434: https://www.linkedin.com/in/zubinkhan1 | D2434: Zubin Khan, MS - Sr. Health Informaticist ... leadership roles focused on leveraging informatics to drive strategic transformation and data-driven decision-making. Connect with me at zubink24@gmail.com ... | E2434: zubink24@gmail.com
